{
  "facts": [
    {
      "id": "nate-001",
      "fact": "Nate Sahr is Noah's friend — gaming buddy",
      "category": "relationship",
      "timestamp": "2026-02-04",
      "source": "conversation",
      "status": "active"
    },
    {
      "id": "nate-002",
      "fact": "His email is natesahr@gmail.com",
      "category": "identity",
      "timestamp": "2026-02-04",
      "source": "email",
      "status": "active"
    },
    {
      "id": "nate-003",
      "fact": "Organized a Seattle Dota trip with Noah in 2023",
      "category": "interest",
      "timestamp": "2026-02-04",
      "source": "email",
      "status": "active"
    },
    {
      "id": "nate-004",
      "fact": "Shares interest in Dota with Noah",
      "category": "interest",
      "timestamp": "2026-02-04",
      "source": "email",
      "status": "active"
    },
    {
      "id": "nate-005",
      "fact": "Still in touch as of Feb 2026 — they talked on Discord today",
      "category": "relationship",
      "timestamp": "2026-02-04",
      "source": "conversation",
      "status": "active"
    }
  ]
}
